Tektronix_TBS2000B_analysis/QuickAnalysis.py
Tektronix_TBS2000B_analysis/__init__.py
Tektronix_TBS2000B_analysis/__main__.py
Tektronix_TBS2000B_control/__init__.py
Tektronix_TBS2000B_control/oscilloscope_control.py
Tektronix_TBS2000B_scripts/__init__.py
Tektronix_TBS2000B_scripts/__main__.py
Tektronix_TBS2000B_scripts/helper_function.py
oscilloscope_scripts_xzf8971-1.2.0.dist-info/LICENSE
oscilloscope_scripts_xzf8971-1.2.0.dist-info/METADATA
oscilloscope_scripts_xzf8971-1.2.0.dist-info/WHEEL
oscilloscope_scripts_xzf8971-1.2.0.dist-info/top_level.txt
oscilloscope_scripts_xzf8971-1.2.0.dist-info/RECORD
