Metadata-Version: 2.1
Name: oscilloscope-scripts-xzf8971
Version: 1.2.0
Summary: A package to control and read data from oscilloscope. Support TekTronix TBS2000B now.
Author-email: Zifeng <zifeng.xu@foxmail.com>
Project-URL: Homepage, https://github.com/xzf89718/oscilloscope_scripts
Project-URL: Bug Tracker, https://github.com/xzf89718/oscilloscope_scripts/issues
Classifier: Programming Language :: Python :: 3
Classifier: License :: OSI Approved :: MIT License
Classifier: Operating System :: OS Independent
Requires-Python: >=3.7
License-File: LICENSE
Requires-Dist: numpy
Requires-Dist: matplotlib
Requires-Dist: pyserial
Requires-Dist: pyvisa
Requires-Dist: pyvisa-py
Requires-Dist: pandas
